jupyterlab_leetcode/__init__.py
jupyterlab_leetcode/_version.py
jupyterlab_leetcode/handlers/__init__.py
jupyterlab_leetcode/handlers/base_handler.py
jupyterlab_leetcode/handlers/cookie_handler.py
jupyterlab_leetcode/handlers/leetcode_handler.py
jupyterlab_leetcode/labextension/package.json
jupyterlab_leetcode/labextension/schemas/jupyterlab-leetcode/package.json.orig
jupyterlab_leetcode/labextension/schemas/jupyterlab-leetcode/plugin.json
jupyterlab_leetcode/labextension/static/300.67e72ac81327ba0034f6.js
jupyterlab_leetcode/labextension/static/404.eab226d41268eeee28d2.js
jupyterlab_leetcode/labextension/static/404.eab226d41268eeee28d2.js.LICENSE.txt
jupyterlab_leetcode/labextension/static/728.7178a816436cbfa78fdf.js
jupyterlab_leetcode/labextension/static/748.c53ec6dfd39996d81eee.js
jupyterlab_leetcode/labextension/static/874.7dc41f4aec1302b2f2f7.js
jupyterlab_leetcode/labextension/static/874.7dc41f4aec1302b2f2f7.js.LICENSE.txt
jupyterlab_leetcode/labextension/static/915.498ec1e8945ed18664d8.js
jupyterlab_leetcode/labextension/static/remoteEntry.e0678b11cac45e1bc153.js
jupyterlab_leetcode/labextension/static/style.js
jupyterlab_leetcode/labextension/static/third-party-licenses.json
jupyterlab_leetcode/tests/__init__.py
jupyterlab_leetcode/tests/test_handlers.py
jupyterlab_leetcode/utils/notebook.template.json
jupyterlab_leetcode/utils/notebook_generator.py
jupyterlab_leetcode/utils/utils.py
jupyterlab_leetcode-0.3.3.data/data/etc/jupyter/jupyter_server_config.d/jupyterlab_leetcode.json
jupyterlab_leetcode-0.3.3.data/data/share/jupyter/labextensions/jupyterlab-leetcode/package.json
jupyterlab_leetcode-0.3.3.data/data/share/jupyter/labextensions/jupyterlab-leetcode/schemas/jupyterlab-leetcode/package.json.orig
jupyterlab_leetcode-0.3.3.data/data/share/jupyter/labextensions/jupyterlab-leetcode/schemas/jupyterlab-leetcode/plugin.json
jupyterlab_leetcode-0.3.3.data/data/share/jupyter/labextensions/jupyterlab-leetcode/static/300.67e72ac81327ba0034f6.js
jupyterlab_leetcode-0.3.3.dist-info/METADATA
jupyterlab_leetcode-0.3.3.dist-info/WHEEL
jupyterlab_leetcode-0.3.3.dist-info/licenses/LICENSE
jupyterlab_leetcode-0.3.3.dist-info/RECORD
